{
  "2025-08-11": {
    "volume": 6584,
    "sentiment": {
      "neutral": 1882,
      "negative": 2909,
      "positive": 1793
    },
    "emotion": {
      "neutral": 495,
      "sadness": 2152,
      "fear": 2213,
      "joy": 811,
      "surprise": 358,
      "disgust": 39,
      "anger": 516
    },
    "language": {
      "en": 4467,
      "en-GB": 8,
      "en-US": 88,
      "ar": 172,
      "de": 36,
      "fr": 16,
      "es": 29,
      "kn": 1,
      "id": 3,
      "it-IT": 1,
      "it": 4,
      "nl": 7,
      "pt": 18,
      "ja": 17,
      "sv": 3,
      "tr": 2,
      "am": 1,
      "an": 1,
      "ko": 6,
      "ca": 2,
      "ru": 1,
      "da": 1,
      "fi": 1,
      "vi": 1,
      "sq": 1,
      "en-AU": 2,
      "uk": 1,
      "aa": 1,
      "zh": 2,
      "sk": 1,
      "la": 2,
      "jp": 1,
      "en-us": 1
    }
  },
  "2025-08-12": {
    "volume": 3313,
    "sentiment": {
      "neutral": 1014,
      "negative": 1561,
      "positive": 738
    },
    "emotion": {
      "fear": 1145,
      "surprise": 186,
      "neutral": 272,
      "sadness": 1001,
      "joy": 413,
      "anger": 279,
      "disgust": 17
    },
    "language": {
      "an": 1,
      "en": 2501,
      "sq": 2,
      "ar": 64,
      "de": 13,
      "en-US": 33,
      "sv": 2,
      "pt": 21,
      "it": 2,
      "es": 11,
      "ja": 3,
      "ko": 2,
      "fr": 13,
      "fi": 1,
      "zh": 2,
      "zh-CN": 1,
      "zh-SG": 1,
      "en-AU": 1,
      "nl": 2,
      "da": 1,
      "am": 2,
      "hy": 1,
      "sv-FI": 1,
      "sv-SE": 1,
      "rn": 1,
      "ru": 2,
      "uk": 2,
      "ak": 1,
      "mk": 1,
      "fa": 1,
      "ro": 1,
      "Fr": 1,
      "en-GB": 2,
      "ab": 1
    }
  },
  "2025-08-13": {
    "volume": 5973,
    "sentiment": {
      "negative": 2895,
      "neutral": 1954,
      "positive": 1124
    },
    "emotion": {
      "disgust": 35,
      "fear": 2111,
      "joy": 784,
      "sadness": 1707,
      "anger": 494,
      "surprise": 344,
      "neutral": 498
    },
    "language": {
      "en": 4445,
      "ar": 297,
      "fr": 25,
      "ro": 2,
      "th": 3,
      "af": 1,
      "pt": 26,
      "en-US": 65,
      "ja": 20,
      "en-GB": 6,
      "fi": 4,
      "sv": 7,
      "nl": 12,
      "de": 25,
      "ko": 9,
      "id": 3,
      "es": 15,
      "it": 1,
      "ae": 1,
      "tl": 1,
      "ru": 4,
      "zh-CN": 1,
      "zh-HK": 1,
      "zh-TW": 1,
      "pl": 3,
      "da": 2,
      "no": 1,
      "en-AU": 2,
      "zh": 1,
      "am": 1,
      "ca": 1,
      "sq": 1,
      "hu": 1,
      "en-us": 1,
      "jp": 1
    }
  },
  "2025-08-14": {
    "volume": 6120,
    "sentiment": {
      "positive": 1439,
      "negative": 2842,
      "neutral": 1839
    },
    "emotion": {
      "fear": 2154,
      "joy": 734,
      "sadness": 1904,
      "neutral": 475,
      "surprise": 346,
      "anger": 476,
      "disgust": 31
    },
    "language": {
      "en": 4123,
      "ar": 348,
      "fr": 19,
      "en-US": 70,
      "pt": 31,
      "sv": 6,
      "it": 2,
      "zh": 4,
      "sq": 4,
      "de": 39,
      "ja": 25,
      "nl": 11,
      "en-GB": 6,
      "th": 1,
      "da": 2,
      "es": 15,
      "ko": 3,
      "ak": 3,
      "fi": 3,
      "ru": 5,
      "zh-CN": 2,
      "zh-HK": 2,
      "zh-TW": 2,
      "tl": 1,
      "ga": 1,
      "af": 1,
      "uk": 1,
      "el": 1,
      "vi": 1,
      "pl": 1,
      "nb": 1,
      "ce": 1,
      "he": 1,
      "ca": 1,
      "as": 1,
      "en-us": 1,
      "en-AU": 1,
      "am": 1,
      "id": 1
    }
  },
  "2025-08-15": {
    "volume": 6633,
    "sentiment": {
      "neutral": 1900,
      "positive": 1903,
      "negative": 2830
    },
    "emotion": {
      "fear": 2230,
      "sadness": 2219,
      "surprise": 359,
      "joy": 853,
      "neutral": 487,
      "anger": 434,
      "disgust": 51
    },
    "language": {
      "en": 4166,
      "de": 28,
      "ar": 368,
      "tl": 1,
      "pt": 25,
      "en-US": 79,
      "ja": 24,
      "fr": 25,
      "en-GB": 5,
      "zh": 2,
      "es": 17,
      "ak": 2,
      "sq": 2,
      "de-DE": 1,
      "tr": 3,
      "la": 1,
      "nb": 3,
      "yi": 1,
      "sk": 1,
      "hy": 1,
      "sv": 4,
      "an": 1,
      "as": 1,
      "ru": 2,
      "fi": 2,
      "aa": 1,
      "et": 1,
      "ab": 1,
      "Angika": 1,
      "ko": 1,
      "it": 1,
      "cy": 1,
      "uk": 1,
      "pl": 1,
      "bg": 1,
      "av": 2,
      "af": 1
    }
  },
  "2025-08-16": {
    "volume": 1192,
    "sentiment": {
      "negative": 591,
      "neutral": 379,
      "positive": 222
    },
    "emotion": {
      "sadness": 364,
      "fear": 388,
      "neutral": 96,
      "surprise": 108,
      "joy": 135,
      "anger": 98,
      "disgust": 3
    },
    "language": {
      "en-US": 22,
      "en": 918,
      "ar": 39,
      "ja": 8,
      "it": 1,
      "ko": 3,
      "sq": 1,
      "pt": 7,
      "zh": 1,
      "fr": 4,
      "de": 3,
      "zh-CN": 2,
      "zh-HK": 2,
      "zh-TW": 2,
      "en-AU": 1,
      "tl": 1,
      "aa": 1,
      "sv": 1,
      "pt-BR": 1,
      "es": 2,
      "fr-FR": 1
    }
  },
  "2025-08-17": {
    "volume": 5875,
    "sentiment": {
      "neutral": 1737,
      "positive": 1434,
      "negative": 2704
    },
    "emotion": {
      "joy": 721,
      "sadness": 2032,
      "fear": 1956,
      "anger": 420,
      "neutral": 378,
      "disgust": 29,
      "surprise": 339
    },
    "language": {
      "en": 3818,
      "en-US": 93,
      "pt": 18,
      "ar": 287,
      "de": 31,
      "ja": 15,
      "sv": 2,
      "fr": 20,
      "nl": 8,
      "ak": 1,
      "ko": 10,
      "zh": 1,
      "es": 15,
      "en-GB": 2,
      "fi": 2,
      "uk": 4,
      "tr": 1,
      "eo": 1,
      "en-AU": 2,
      "th": 1,
      "id": 2,
      "it": 1,
      "ht": 1,
      "am": 1,
      "sq": 2,
      "nb": 1,
      "pl": 1,
      "zh-CN": 1,
      "zh-HK": 1,
      "zh-TW": 1,
      "hu": 1,
      "is": 2
    }
  }
}