{
  "2026-03-02": {
    "volume": 1511,
    "sentiment": {
      "negative": 196,
      "neutral": 1239,
      "positive": 76
    },
    "emotion": {
      "anger": 84,
      "fear": 776,
      "neutral": 380,
      "joy": 112,
      "sadness": 94,
      "disgust": 7,
      "surprise": 58
    },
    "language": {
      "pt": 46,
      "en": 529,
      "ja": 33,
      "nb": 190,
      "sv": 241,
      "no": 26,
      "nb-NO": 44,
      "sv-FI": 2,
      "sv-SE": 63,
      "nn": 12,
      "en-US": 50,
      "de": 22,
      "da": 1,
      "el": 1,
      "es": 11,
      "cs": 6,
      "tr": 19,
      "fr": 12,
      "ga": 2,
      "ro": 1,
      "zh": 1,
      "ja-JP": 1,
      "ko": 2,
      "fi": 2,
      "uk": 2,
      "nl": 2,
      "it-IT": 1,
      "it": 4,
      "no-NO": 6,
      "pl": 1,
      "fi-FI": 1,
      "la": 1,
      "de-DE": 1,
      "nl-NL": 1,
      "sl": 1,
      "lv-LV": 1,
      "lv": 1,
      "ca": 1
    }
  },
  "2026-03-03": {
    "volume": 1329,
    "sentiment": {
      "neutral": 1086,
      "negative": 167,
      "positive": 76
    },
    "emotion": {
      "fear": 648,
      "joy": 107,
      "neutral": 333,
      "sadness": 91,
      "anger": 100,
      "surprise": 42,
      "disgust": 8
    },
    "language": {
      "en": 482,
      "ja": 32,
      "sv": 222,
      "en-US": 51,
      "nn": 4,
      "nb-NO": 50,
      "nb": 154,
      "pt": 45,
      "tr": 6,
      "ga": 1,
      "no": 28,
      "no-NO": 7,
      "sv-FI": 5,
      "sv-SE": 50,
      "sl": 1,
      "de": 7,
      "es": 11,
      "zh": 1,
      "lv": 3,
      "cs": 6,
      "fr": 8,
      "ca": 2,
      "it": 2,
      "en-AU": 1,
      "lt-LT": 2,
      "lt": 2,
      "lv-LV": 1,
      "fi": 1,
      "ro": 1
    }
  },
  "2026-03-04": {
    "volume": 1393,
    "sentiment": {
      "positive": 79,
      "negative": 179,
      "neutral": 1135
    },
    "emotion": {
      "joy": 133,
      "anger": 93,
      "sadness": 104,
      "fear": 664,
      "neutral": 336,
      "surprise": 52,
      "disgust": 11
    },
    "language": {
      "en-US": 72,
      "en": 486,
      "nb": 135,
      "sv": 246,
      "ja": 32,
      "pt": 39,
      "sv-SE": 37,
      "nb-NO": 40,
      "no": 21,
      "sv-FI": 5,
      "fr": 12,
      "es": 8,
      "de": 8,
      "fr-FR": 1,
      "nn": 10,
      "ca": 4,
      "ko": 1,
      "uk": 1,
      "it": 1,
      "ro": 2,
      "tr": 4,
      "ur": 1,
      "no-NO": 2,
      "el": 1,
      "sl": 1,
      "sk": 1
    }
  },
  "2026-03-05": {
    "volume": 1361,
    "sentiment": {
      "neutral": 1141,
      "negative": 142,
      "positive": 78
    },
    "emotion": {
      "neutral": 370,
      "fear": 688,
      "anger": 71,
      "sadness": 82,
      "joy": 99,
      "surprise": 43,
      "disgust": 8
    },
    "language": {
      "pt": 41,
      "en": 432,
      "es": 13,
      "cs": 3,
      "nb": 160,
      "de": 7,
      "th": 1,
      "sv-FI": 8,
      "sv-SE": 68,
      "ca": 3,
      "en-US": 54,
      "nb-NO": 25,
      "sv": 271,
      "tr": 7,
      "ja": 47,
      "et": 1,
      "fr": 9,
      "no": 15,
      "nn": 9,
      "nl": 3,
      "pl": 1,
      "ru": 2,
      "it": 2,
      "ko": 5,
      "da": 2,
      "lt-LT": 1,
      "lt": 1,
      "ak": 1,
      "sq": 1,
      "lv-LV": 1,
      "lv": 1
    }
  },
  "2026-03-06": {
    "volume": 1481,
    "sentiment": {
      "neutral": 1223,
      "negative": 170,
      "positive": 88
    },
    "emotion": {
      "joy": 130,
      "fear": 733,
      "surprise": 56,
      "neutral": 374,
      "sadness": 111,
      "anger": 70,
      "disgust": 7
    },
    "language": {
      "pt": 53,
      "en": 487,
      "es": 7,
      "ca": 5,
      "sv": 288,
      "en-US": 37,
      "nb-NO": 43,
      "nb": 163,
      "sv-SE": 47,
      "ja": 35,
      "sv-FI": 2,
      "ko": 4,
      "no": 19,
      "ak": 1,
      "sq": 1,
      "nn": 17,
      "de": 7,
      "fr": 10,
      "zh": 2,
      "pt-PT": 1,
      "it": 3,
      "cs": 2,
      "nl": 4,
      "tr": 4,
      "sk": 2,
      "hi": 1,
      "it-IT": 1,
      "en-AU": 1,
      "en-us": 1,
      "lv-LV": 1,
      "lv": 1,
      "en-GB": 1,
      "th": 1,
      "se": 1
    }
  },
  "2026-03-07": {
    "volume": 1328,
    "sentiment": {
      "negative": 154,
      "neutral": 1101,
      "positive": 73
    },
    "emotion": {
      "anger": 75,
      "neutral": 313,
      "fear": 691,
      "sadness": 83,
      "joy": 104,
      "disgust": 7,
      "surprise": 55
    },
    "language": {
      "sv": 246,
      "en-US": 26,
      "nb-NO": 42,
      "nb": 157,
      "sv-SE": 35,
      "en": 497,
      "pt": 35,
      "fr": 13,
      "ja": 40,
      "no": 13,
      "es": 18,
      "nn": 8,
      "eu": 1,
      "de": 7,
      "da": 2,
      "cs": 5,
      "cy": 1,
      "ko": 1,
      "pl": 1,
      "it": 1,
      "uk": 4,
      "tr": 2,
      "no-NO": 1,
      "zh": 6,
      "nl": 3,
      "sk": 4,
      "lv-LV": 1,
      "lv": 1,
      "sv-FI": 2,
      "ro": 2,
      "sq": 2,
      "ak": 1,
      "gl": 1
    }
  },
  "2026-03-08": {
    "volume": 1254,
    "sentiment": {
      "neutral": 967,
      "positive": 119,
      "negative": 168
    },
    "emotion": {
      "fear": 673,
      "neutral": 261,
      "joy": 107,
      "surprise": 41,
      "sadness": 88,
      "anger": 79,
      "disgust": 5
    },
    "language": {
      "en": 470,
      "nl": 1,
      "nn": 6,
      "sv": 230,
      "es": 10,
      "en-US": 26,
      "nb": 158,
      "no": 21,
      "nb-NO": 46,
      "en-GB": 2,
      "ja": 28,
      "sv-SE": 41,
      "pt": 33,
      "cs": 1,
      "fr": 13,
      "tr": 6,
      "th": 3,
      "de": 3,
      "it": 1,
      "sv-FI": 4,
      "pt-PT": 1,
      "en-AU": 1,
      "ro": 1,
      "eu": 1,
      "lv-LV": 1,
      "lv": 1,
      "el": 1,
      "sk": 1
    }
  }
}