{
  "topic_0": {
    "joy": 228,
    "neutral": 1331,
    "anger": 128,
    "fear": 1844,
    "surprise": 149,
    "sadness": 137,
    "disgust": 23
  },
  "topic_6": {
    "fear": 364,
    "neutral": 142,
    "anger": 127,
    "sadness": 123,
    "joy": 35,
    "surprise": 40,
    "disgust": 17
  },
  "topic_5": {
    "fear": 697,
    "sadness": 139,
    "joy": 111,
    "surprise": 71,
    "neutral": 299,
    "anger": 100,
    "disgust": 9
  },
  "topic_7": {
    "fear": 484,
    "neutral": 259,
    "anger": 65,
    "joy": 54,
    "sadness": 41,
    "disgust": 14,
    "surprise": 48
  },
  "topic_1": {
    "fear": 760,
    "neutral": 538,
    "anger": 93,
    "disgust": 9,
    "joy": 280,
    "sadness": 154,
    "surprise": 200
  },
  "topic_3": {
    "neutral": 247,
    "fear": 230,
    "joy": 71,
    "sadness": 60,
    "anger": 60,
    "surprise": 37,
    "disgust": 5
  },
  "topic_4": {
    "joy": 46,
    "neutral": 220,
    "sadness": 81,
    "anger": 53,
    "fear": 279,
    "disgust": 2,
    "surprise": 29
  },
  "topic_2": {
    "neutral": 301,
    "fear": 162,
    "joy": 125,
    "anger": 42,
    "sadness": 57,
    "surprise": 55,
    "disgust": 3
  }
}