{
  "topic_0": {
    "neutral": 935,
    "fear": 1873,
    "sadness": 66,
    "joy": 93,
    "anger": 46,
    "disgust": 15,
    "surprise": 20
  },
  "topic_6": {
    "fear": 319,
    "neutral": 152,
    "joy": 39,
    "anger": 43,
    "sadness": 63,
    "surprise": 36,
    "disgust": 1
  },
  "topic_5": {
    "fear": 666,
    "neutral": 168,
    "anger": 72,
    "disgust": 8,
    "joy": 31,
    "sadness": 50,
    "surprise": 21
  },
  "topic_3": {
    "neutral": 243,
    "anger": 81,
    "surprise": 49,
    "fear": 326,
    "joy": 124,
    "sadness": 65,
    "disgust": 8
  },
  "topic_7": {
    "sadness": 82,
    "fear": 243,
    "joy": 61,
    "neutral": 255,
    "surprise": 50,
    "anger": 94,
    "disgust": 7
  },
  "topic_1": {
    "joy": 371,
    "fear": 290,
    "neutral": 332,
    "sadness": 151,
    "anger": 90,
    "surprise": 125,
    "disgust": 11
  },
  "topic_4": {
    "sadness": 95,
    "neutral": 178,
    "surprise": 20,
    "fear": 547,
    "anger": 63,
    "joy": 21,
    "disgust": 10
  },
  "topic_2": {
    "neutral": 268,
    "fear": 216,
    "joy": 79,
    "anger": 67,
    "disgust": 3,
    "surprise": 31,
    "sadness": 44
  }
}