{
  "topic_6": {
    "surprise": 76,
    "neutral": 191,
    "joy": 260,
    "fear": 388,
    "sadness": 477,
    "anger": 119,
    "disgust": 17
  },
  "topic_1": {
    "disgust": 106,
    "fear": 3795,
    "sadness": 3520,
    "surprise": 993,
    "anger": 1175,
    "neutral": 883,
    "joy": 1498
  },
  "topic_0": {
    "sadness": 3204,
    "joy": 477,
    "fear": 1389,
    "anger": 132,
    "surprise": 116,
    "neutral": 375,
    "disgust": 28
  },
  "topic_4": {
    "sadness": 687,
    "joy": 216,
    "disgust": 7,
    "surprise": 94,
    "anger": 162,
    "fear": 668,
    "neutral": 143
  },
  "topic_7": {
    "joy": 285,
    "sadness": 822,
    "anger": 166,
    "neutral": 161,
    "fear": 1041,
    "surprise": 108,
    "disgust": 23
  },
  "topic_2": {
    "sadness": 929,
    "fear": 1172,
    "anger": 257,
    "neutral": 417,
    "surprise": 218,
    "joy": 373,
    "disgust": 30
  },
  "topic_5": {
    "fear": 469,
    "joy": 154,
    "sadness": 659,
    "surprise": 83,
    "anger": 119,
    "neutral": 129,
    "disgust": 7
  },
  "topic_3": {
    "joy": 289,
    "surprise": 111,
    "sadness": 1162,
    "anger": 135,
    "fear": 475,
    "neutral": 140,
    "disgust": 12
  }
}