{
  "date": "2025-06-22",
  "complete": {
    "total_posts": 97447,
    "total_sentiments": 3,
    "total_emotions": 7,
    "total_languages": 90,
    "total_topics": 8,
    "total_hashtags": 26899,
    "total_emojis": 773
  },
  "last_week": {
    "total_posts": 31743,
    "total_sentiments": 3,
    "total_emotions": 7,
    "total_languages": 67,
    "total_topics": 8,
    "total_hashtags": 10602,
    "total_emojis": 594
  },
  "averages": {
    "avg_posts_per_day": 4534.71,
    "avg_hashtags_per_day": 2703.29,
    "avg_emojis_per_day": 1449.29
  },
  "top": {
    "sentiment": "negative",
    "emotion": "fear",
    "language": "en",
    "hashtag": "#art",
    "emoji": "😭"
  }
}