{
  "date": "2025-08-31",
  "complete": {
    "total_posts": 381834,
    "total_sentiments": 3,
    "total_emotions": 7,
    "total_languages": 104,
    "total_topics": 8,
    "total_hashtags": 74572,
    "total_emojis": 904
  },
  "last_week": {
    "total_posts": 1830,
    "total_sentiments": 3,
    "total_emotions": 7,
    "total_languages": 23,
    "total_topics": 8,
    "total_hashtags": 913,
    "total_emojis": 171
  },
  "averages": {
    "avg_posts_per_day": 261.43,
    "avg_hashtags_per_day": 156.0,
    "avg_emojis_per_day": 75.86
  },
  "top": {
    "sentiment": "negative",
    "emotion": "sadness",
    "language": "en",
    "hashtag": "#ParentingTips",
    "emoji": "🙏"
  }
}