{
  "topic_3": {
    "negative": 875,
    "neutral": 994,
    "positive": 425
  },
  "topic_5": {
    "negative": 753,
    "neutral": 940,
    "positive": 351
  },
  "topic_7": {
    "neutral": 1110,
    "negative": 905,
    "positive": 533
  },
  "topic_1": {
    "negative": 3699,
    "neutral": 2446,
    "positive": 1147
  },
  "topic_0": {
    "negative": 7814,
    "neutral": 5191,
    "positive": 2653
  },
  "topic_4": {
    "positive": 461,
    "neutral": 1036,
    "negative": 884
  },
  "topic_6": {
    "negative": 763,
    "neutral": 1027,
    "positive": 396
  },
  "topic_2": {
    "positive": 533,
    "negative": 1086,
    "neutral": 920
  }
}