{
  "topic_5": {
    "negative": 330,
    "neutral": 456,
    "positive": 173
  },
  "topic_1": {
    "negative": 3019,
    "neutral": 1647,
    "positive": 1041
  },
  "topic_0": {
    "neutral": 2425,
    "negative": 2995,
    "positive": 1060
  },
  "topic_7": {
    "neutral": 575,
    "negative": 377,
    "positive": 267
  },
  "topic_2": {
    "neutral": 530,
    "negative": 622,
    "positive": 338
  },
  "topic_3": {
    "negative": 740,
    "neutral": 552,
    "positive": 339
  },
  "topic_6": {
    "positive": 187,
    "negative": 359,
    "neutral": 438
  },
  "topic_4": {
    "neutral": 666,
    "positive": 387,
    "negative": 431
  }
}