{
  "topic_0": {
    "positive": 2695,
    "negative": 8130,
    "neutral": 5241
  },
  "topic_3": {
    "neutral": 1046,
    "positive": 383,
    "negative": 906
  },
  "topic_7": {
    "negative": 747,
    "neutral": 894,
    "positive": 398
  },
  "topic_6": {
    "neutral": 1102,
    "negative": 776,
    "positive": 423
  },
  "topic_5": {
    "negative": 846,
    "positive": 404,
    "neutral": 1077
  },
  "topic_4": {
    "negative": 887,
    "neutral": 999,
    "positive": 468
  },
  "topic_1": {
    "positive": 1140,
    "negative": 3746,
    "neutral": 2509
  },
  "topic_2": {
    "neutral": 1032,
    "negative": 1106,
    "positive": 535
  }
}