{
  "topic_0": {
    "negative": 3003,
    "positive": 1048,
    "neutral": 2321
  },
  "topic_3": {
    "neutral": 531,
    "negative": 611,
    "positive": 277
  },
  "topic_4": {
    "negative": 538,
    "positive": 336,
    "neutral": 596
  },
  "topic_6": {
    "neutral": 630,
    "positive": 420,
    "negative": 805
  },
  "topic_1": {
    "negative": 2549,
    "positive": 877,
    "neutral": 1444
  },
  "topic_2": {
    "negative": 827,
    "positive": 333,
    "neutral": 526
  },
  "topic_7": {
    "neutral": 636,
    "negative": 916,
    "positive": 279
  },
  "topic_5": {
    "neutral": 706,
    "positive": 332,
    "negative": 495
  }
}