{
  "topic_5": {
    "negative": 712,
    "neutral": 677,
    "positive": 325
  },
  "topic_1": {
    "neutral": 1970,
    "negative": 3083,
    "positive": 1096
  },
  "topic_3": {
    "negative": 877,
    "positive": 372,
    "neutral": 520
  },
  "topic_7": {
    "neutral": 730,
    "positive": 316,
    "negative": 776
  },
  "topic_0": {
    "neutral": 2798,
    "negative": 5009,
    "positive": 1555
  },
  "topic_6": {
    "negative": 834,
    "neutral": 641,
    "positive": 333
  },
  "topic_4": {
    "neutral": 665,
    "negative": 912,
    "positive": 338
  },
  "topic_2": {
    "negative": 1006,
    "neutral": 1238,
    "positive": 398
  }
}