{
  "topic_1": {
    "positive": 1058,
    "neutral": 1807,
    "negative": 4293
  },
  "topic_4": {
    "negative": 956,
    "positive": 440,
    "neutral": 802
  },
  "topic_0": {
    "negative": 4131,
    "neutral": 3231,
    "positive": 3747
  },
  "topic_6": {
    "positive": 564,
    "neutral": 956,
    "negative": 862
  },
  "topic_7": {
    "negative": 1154,
    "neutral": 1267,
    "positive": 666
  },
  "topic_2": {
    "positive": 1252,
    "negative": 2896,
    "neutral": 1689
  },
  "topic_5": {
    "neutral": 782,
    "negative": 939,
    "positive": 370
  },
  "topic_3": {
    "negative": 1078,
    "positive": 379,
    "neutral": 666
  }
}