{
  "topic_0": {
    "label": [
      "av",
      "på",
      "er",
      "det",
      "en"
    ],
    "count": 3753,
    "daily": {
      "2026-06-06": 398,
      "2026-06-07": 461,
      "2026-06-08": 593,
      "2026-06-09": 615,
      "2026-06-10": 433,
      "2026-06-11": 725,
      "2026-06-12": 528
    },
    "sentiment": {
      "neutral": 3644,
      "negative": 66,
      "positive": 43
    },
    "emotion": {
      "neutral": 1343,
      "fear": 2152,
      "surprise": 46,
      "anger": 69,
      "joy": 85,
      "sadness": 38,
      "disgust": 20
    },
    "hashtags": [
      "#celebplanes",
      "#celebjettracking",
      "#privatejet",
      "#avgeek",
      "#insynsregistret",
      "#AV",
      "#FANZA",
      "#porn",
      "#R18",
      "#sex"
    ],
    "emojis": [
      "👇",
      "🚨",
      "🔽",
      "♡",
      "🔥",
      "🇺",
      "👉",
      "★",
      "🇳",
      "🇴"
    ]
  },
  "topic_4": {
    "label": [
      "stalled",
      "new",
      "autonomy",
      "la",
      "just"
    ],
    "count": 919,
    "daily": {
      "2026-06-06": 94,
      "2026-06-07": 55,
      "2026-06-08": 171,
      "2026-06-09": 59,
      "2026-06-10": 222,
      "2026-06-11": 202,
      "2026-06-12": 116
    },
    "sentiment": {
      "neutral": 757,
      "negative": 134,
      "positive": 28
    },
    "emotion": {
      "neutral": 248,
      "fear": 470,
      "anger": 55,
      "sadness": 70,
      "joy": 45,
      "surprise": 23,
      "disgust": 8
    },
    "hashtags": [
      "#celebplanes",
      "#celebjettracking",
      "#privatejet",
      "#avgeek",
      "#insynsregistret",
      "#AV",
      "#FANZA",
      "#R18",
      "#nsfw",
      "#porn"
    ],
    "emojis": [
      "🚨",
      "👇",
      "🔽",
      "🔥",
      "👉",
      "🇺",
      "🇴",
      "♂",
      "🇷",
      "🛒"
    ]
  },
  "topic_1": {
    "label": [
      "cruise",
      "gal",
      "ship",
      "tom",
      "just"
    ],
    "count": 1936,
    "daily": {
      "2026-06-06": 198,
      "2026-06-07": 227,
      "2026-06-08": 203,
      "2026-06-09": 287,
      "2026-06-10": 315,
      "2026-06-11": 344,
      "2026-06-12": 362
    },
    "sentiment": {
      "positive": 359,
      "neutral": 1265,
      "negative": 312
    },
    "emotion": {
      "joy": 408,
      "fear": 445,
      "surprise": 345,
      "neutral": 454,
      "anger": 99,
      "sadness": 176,
      "disgust": 9
    },
    "hashtags": [
      "#celebplanes",
      "#celebjettracking",
      "#privatejet",
      "#avgeek",
      "#insynsregistret",
      "#FANZA",
      "#AV",
      "#nyc",
      "#mta",
      "#subway"
    ],
    "emojis": [
      "🚨",
      "👇",
      "🔽",
      "🛒",
      "♡",
      "🇺",
      "★",
      "💫",
      "🇦",
      "🚢"
    ]
  },
  "topic_2": {
    "label": [
      "購入pr",
      "女優判定",
      "ティッシュシコレール",
      "waymo",
      "trains"
    ],
    "count": 907,
    "daily": {
      "2026-06-06": 301,
      "2026-06-07": 100,
      "2026-06-08": 81,
      "2026-06-09": 207,
      "2026-06-10": 43,
      "2026-06-11": 105,
      "2026-06-12": 70
    },
    "sentiment": {
      "positive": 30,
      "neutral": 743,
      "negative": 134
    },
    "emotion": {
      "surprise": 196,
      "anger": 31,
      "joy": 84,
      "sadness": 147,
      "fear": 161,
      "neutral": 287,
      "disgust": 1
    },
    "hashtags": [
      "#celebplanes",
      "#celebjettracking",
      "#privatejet",
      "#avgeek",
      "#gulfstreamg650er",
      "#hess",
      "#gulfstreamg650",
      "#insynsregistret",
      "#laurenepowelljobs",
      "#AV"
    ],
    "emojis": [
      "🚨",
      "👇",
      "🔽",
      "🇺",
      "🔥",
      "🇦",
      "🌟",
      "⚠",
      "☆",
      "🚇"
    ]
  },
  "topic_7": {
    "label": [
      "och",
      "är",
      "att",
      "för",
      "jag"
    ],
    "count": 1297,
    "daily": {
      "2026-06-06": 191,
      "2026-06-07": 203,
      "2026-06-08": 274,
      "2026-06-09": 122,
      "2026-06-10": 110,
      "2026-06-11": 167,
      "2026-06-12": 230
    },
    "sentiment": {
      "neutral": 1202,
      "negative": 70,
      "positive": 25
    },
    "emotion": {
      "neutral": 451,
      "fear": 664,
      "anger": 52,
      "sadness": 51,
      "surprise": 32,
      "joy": 39,
      "disgust": 8
    },
    "hashtags": [
      "#celebplanes",
      "#celebjettracking",
      "#privatejet",
      "#avgeek",
      "#FANZA",
      "#insynsregistret",
      "#porn",
      "#nsfw",
      "#sex",
      "#adult"
    ],
    "emojis": [
      "👇",
      "🚨",
      "★",
      "🔽",
      "🇺",
      "🇳",
      "🇴",
      "♡",
      "👉",
      "👀"
    ]
  },
  "topic_3": {
    "label": [
      "ab",
      "aktier",
      "sek",
      "rapporterar",
      "genomfört"
    ],
    "count": 981,
    "daily": {
      "2026-06-06": 239,
      "2026-06-07": 142,
      "2026-06-08": 113,
      "2026-06-09": 112,
      "2026-06-10": 134,
      "2026-06-11": 166,
      "2026-06-12": 75
    },
    "sentiment": {
      "neutral": 794,
      "negative": 147,
      "positive": 40
    },
    "emotion": {
      "fear": 421,
      "neutral": 264,
      "anger": 74,
      "joy": 60,
      "disgust": 4,
      "surprise": 36,
      "sadness": 122
    },
    "hashtags": [
      "#celebplanes",
      "#celebjettracking",
      "#privatejet",
      "#avgeek",
      "#AV",
      "#FANZA",
      "#nsfw",
      "#av",
      "#nyc",
      "#mta"
    ],
    "emojis": [
      "👇",
      "🔥",
      "🚨",
      "🔽",
      "♡",
      "🇺",
      "🇸",
      "🇪",
      "🇦",
      "🎓"
    ]
  },
  "topic_5": {
    "label": [
      "autonomy",
      "ai",
      "people",
      "like",
      "just"
    ],
    "count": 895,
    "daily": {
      "2026-06-06": 156,
      "2026-06-07": 119,
      "2026-06-08": 145,
      "2026-06-09": 57,
      "2026-06-10": 166,
      "2026-06-11": 135,
      "2026-06-12": 117
    },
    "sentiment": {
      "neutral": 622,
      "positive": 56,
      "negative": 217
    },
    "emotion": {
      "joy": 91,
      "fear": 264,
      "neutral": 205,
      "sadness": 113,
      "anger": 112,
      "surprise": 109,
      "disgust": 1
    },
    "hashtags": [
      "#celebplanes",
      "#celebjettracking",
      "#privatejet",
      "#avgeek",
      "#insynsregistret",
      "#FANZA",
      "#AV",
      "#av",
      "#nyc",
      "#mta"
    ],
    "emojis": [
      "👇",
      "🚨",
      "🔽",
      "📍",
      "★",
      "🇺",
      "📰",
      "📅",
      "🕒",
      "🔥"
    ]
  },
  "topic_6": {
    "label": [
      "av",
      "trains",
      "train",
      "running",
      "line"
    ],
    "count": 783,
    "daily": {
      "2026-06-06": 70,
      "2026-06-07": 28,
      "2026-06-08": 148,
      "2026-06-09": 114,
      "2026-06-10": 160,
      "2026-06-11": 68,
      "2026-06-12": 195
    },
    "sentiment": {
      "neutral": 726,
      "negative": 36,
      "positive": 21
    },
    "emotion": {
      "surprise": 131,
      "neutral": 223,
      "joy": 44,
      "sadness": 51,
      "anger": 22,
      "fear": 306,
      "disgust": 6
    },
    "hashtags": [
      "#celebplanes",
      "#celebjettracking",
      "#privatejet",
      "#avgeek",
      "#dassaultfalcon7x",
      "#taylorswift",
      "#insynsregistret",
      "#FANZA",
      "#nyc",
      "#mta"
    ],
    "emojis": [
      "👇",
      "🚨",
      "★",
      "🇳",
      "🇴",
      "🔽",
      "👉",
      "📡",
      "🇺",
      "🌐"
    ]
  }
}